{"data":{"ratings":[{"orderid":104652925582122,"itemid":17839269862,"cmtid":8300086275,"ctime":1651934164,"rating":1,"userid":127544681,"shopid":494676223,"comment":"Công dụng:xài cỡ 1 tuần thấy có dưỡng ẩm, đẩy mụn ẩn nhẹ\nKhả năng thẩm thấu:hợp vs da dầu\n\nNên mua nha, xài thích lắm, xài thường xuyên để duy trì da","rating_star":5,"status":2,"mtime":1671164466,"editable":0,"opt":2,"filter":7,"mentioned":null,"is_hidden":false,"author_username":"b*****g","author_portrait":"e21b5d9afc52ef2e82b57f6033dda7fe","author_shopid":127542857,"anonymous":true,"images":["1aa824947ae133a65d0d330962f220a0","44bcc739dc1995ddde95cc593acc1ee3","cdd0a50e9c85c4e06ed84a1fc244f8e1","2d2073c3005a73c113fad4e8ae117786","28319426bbed50723773285a0c7ac1c8"],"videos":[{"id":"vn_69e42635-e7b4-4523-8c53-4bf75f6c48a3_000147","cover":"https://play-ws.vod.shopee.com/c3/98934353/103/Anoy8PkAyD7KewIh6QEAAEc.jpg","url":"https://play-ws.vod.shopee.com/c3/98934353/103/Anoyx8MASKnKewIhDAINAEY.mp4","duration":10997,"upload_time":null,"mms_ext":"{\"vid\":\"vn_69e42635-e7b4-4523-8c53-4bf75f6c48a3_000147\",\"biz\":103,\"duration\":11000,\"create_time\":1651934136,\"serviceID\":2,\"cover\":\"http://play-ws.vod.shopee.com/c3/98934353/103/Anoy8PkAyD7KewIh6QEAAEc.jpg\",\"cover_list\":null,\"formats\":[{\"format\":1600005,\"defn\":\"V640P\",\"profile\":\"MP4\",\"path\":\"\",\"url\":\"http://play-ws.vod.shopee.com/c3/98934353/103/Anoyx8MASKnKewIhDAINAEY.mp4\",\"width\":640,\"height\":1138,\"bitrate\":852520,\"size\":1176212,\"fps\":25,\"duration\":11000,\"update_time\":1651934145}],\"default_format\":{\"format\":600001,\"defn\":\"ORI\",\"profile\":\"MP4\",\"path\":\"\",\"url\":\"http://play-ws.vod.shopee.com/c3/98934353/103/AnoyVncAYEHKewIh8wEGAEY.mp4\",\"width\":720,\"height\":1280,\"bitrate\":1498508,\"size\":2061885,\"fps\":24.09709,\"duration\":10997,\"update_time\":1651934138},\"extend_formats\":{\"H265\":[{\"format\":1600022,\"defn\":\"V640P\",\"profile\":\"MP4\",\"path\":\"\",\"url\":\"http://play-ws.vod.shopee.com/c3/98934353/103/A3oxONXPAATO4HEREYwJACc.mp4\",\"width\":640,\"height\":1138,\"bitrate\":421286,\"size\":589240,\"fps\":25.09025,\"duration\":11079,\"update_time\":1667998692}]},\"ab_test\":\"\"}","cover_image_id":""}],"product_items":[{"itemid":17839269862,"shopid":494676223,"name":"Serum Mụn SKINTIFIC Chính Hãng Rulya Anti Acne 20ml","image":"afd17f8a1920780ccd39a6dbb9e6f358","is_snapshot":1,"snapshotid":3488484281,"modelid":135025837391,"model_name":"","options":[""]}],"delete_reason":null,"delete_operator":null,"ItemRatingReply":null,"tags":[{"tag_id":2,"tag_description":"Chất lượng sản phẩm tuyệt vời"},{"tag_id":5,"tag_description":"Đóng gói sản phẩm rất đẹp và chắc chắn"},{"tag_id":3,"tag_description":"Rất đáng tiền"},{"tag_id":4,"tag_description":"Thời gian giao hàng rất nhanh"}],"editable_date":1654526164,"show_reply":null,"like_count":3,"liked":null,"sync_to_social":false,"detailed_rating":{"product_quality":5,"seller_service":null,"delivery_service":null},"exclude_scoring_due_low_logistic":false,"loyalty_info":null,"template_tags":["Công dụng","Khả năng thẩm thấu"],"has_template_tag":true,"sync_to_social_toggle":null,"sip_info":{"is_oversea":false,"origin_region":"vn"},"is_repeated_purchase":false,"display_variation_filter":null,"overall_fit":0,"is_normal_item":true,"viewed":null,"show_view":null,"sync_to_social_detail":null,"profile":null,"size_info_tags":null,"size_info_abt":"","image_data":[{"image_id":"1aa824947ae133a65d0d330962f220a0","cover_image_id":"1aa824947ae133a65d0d330962f220a0"},{"image_id":"44bcc739dc1995ddde95cc593acc1ee3","cover_image_id":"44bcc739dc1995ddde95cc593acc1ee3"},{"image_id":"cdd0a50e9c85c4e06ed84a1fc244f8e1","cover_image_id":"cdd0a50e9c85c4e06ed84a1fc244f8e1"},{"image_id":"2d2073c3005a73c113fad4e8ae117786","cover_image_id":"2d2073c3005a73c113fad4e8ae117786"},{"image_id":"28319426bbed50723773285a0c7ac1c8","cover_image_id":"28319426bbed50723773285a0c7ac1c8"}],"key_media":{"key_media_code":0,"key_media_id":""}},{"orderid":125259189175498,"itemid":17839269862,"cmtid":10386473436,"ctime":1671781706,"rating":1,"userid":391499924,"shopid":494676223,"comment":"Công dụng:trị mụn và thâm\nMùi hương:không biết\nDành cho da:dầu\n\nChưa sử dụng nên không biết công dụng ra sao. Đóng gói cẩn thận","rating_star":5,"status":2,"mtime":1671781706,"editable":1,"opt":2,"filter":7,"mentioned":null,"is_hidden":false,"author_username":"nguyenkimchi1312_2001","author_portrait":"7e5e87f218d4ed4cf3704ab0ff724201","author_shopid":391480347,"anonymous":false,"images":["vn-11134103-22120-68ixdb6abflv04","vn-11134103-22120-6jke65abbflv01","vn-11134103-22120-xdaoi8kbbflvc2","vn-11134103-22120-d7ieshpbbflv16","vn-11134103-22120-xxt93qvbbflve6"],"videos":[{"id":"vn_679240cf-0d4e-45e9-a8d9-ca1a138b2e77_000219","cover":"https://img.sp.mms.shopee.sg/vn-11110103-22120-wxl7j8tabflv8c","url":"https://play-ws.vod.shopee.com/api/v4/11110103/mms/vn_679240cf-0d4e-45e9-a8d9-ca1a138b2e77_000219.16000051671781651.mp4","duration":8126,"upload_time":null,"mms_ext":"{\"vid\":\"vn_679240cf-0d4e-45e9-a8d9-ca1a138b2e77_000219\",\"biz\":103,\"duration\":8126,\"create_time\":1671781650,\"serviceID\":2,\"cover\":\"https://img.sp.mms.shopee.sg/vn-11110103-22120-wxl7j8tabflv8c\",\"cover_list\":null,\"formats\":[{\"format\":1600005,\"defn\":\"V640P\",\"profile\":\"MP4\",\"path\":\"\",\"url\":\"http://play-ws.vod.shopee.com/api/v4/11110103/mms/vn_679240cf-0d4e-45e9-a8d9-ca1a138b2e77_000219.16000051671781651.mp4\",\"width\":640,\"height\":1138,\"bitrate\":784580,\"size\":895043,\"fps\":25.12438,\"duration\":8126,\"update_time\":1671781656},{\"format\":1600046,\"defn\":\"V480P\",\"profile\":\"MP4\",\"path\":\"\",\"url\":\"http://play-ws.vod.shopee.com/api/v4/11110103/mms/vn_679240cf-0d4e-45e9-a8d9-ca1a138b2e77_000219.12000461671781655.mp4\",\"width\":480,\"height\":854,\"bitrate\":642050,\"size\":755302,\"fps\":25,\"duration\":8151,\"update_time\":1671781655}],\"default_format\":{\"format\":600001,\"defn\":\"ORI\",\"profile\":\"MP4\",\"path\":\"\",\"url\":\"http://play-ws.vod.shopee.com/api/v4/11110103/mms/vn_679240cf-0d4e-45e9-a8d9-ca1a138b2e77_000219.ori.mp4\",\"width\":720,\"height\":1280,\"bitrate\":3500393,\"size\":3687438,\"fps\":13.92569,\"duration\":8126,\"update_time\":1671781652},\"extend_formats\":{\"H265\":[{\"format\":1600022,\"defn\":\"V640P\",\"profile\":\"MP4\",\"path\":\"\",\"url\":\"http://play-ws.vod.shopee.com/api/v4/11110103/mms/vn_679240cf-0d4e-45e9-a8d9-ca1a138b2e77_000219.16000221671781651.mp4\",\"width\":640,\"height\":1138,\"bitrate\":677274,\"size\":820701,\"fps\":25.12438,\"duration\":8081,\"update_time\":1671781666}]},\"ab_test\":\"\"}","cover_image_id":""}],"product_items":[{"itemid":17839269862,"shopid":494676223,"name":"Serum Mụn SKINTIFIC Chính Hãng Rulya Anti Acne 20ml","image":"2b53ac82ad54eff1c131b77f58a624dd","is_snapshot":1,"snapshotid":7800276695,"modelid":135025837391,"model_name":"","options":[""]}],"delete_reason":null,"delete_operator":null,"ItemRatingReply":null,"tags":null,"editable_date":1674373706,"show_reply":null,"like_count":null,"liked":null,"sync_to_social":false,"detailed_rating":{"product_quality":5,"seller_service":5,"delivery_service":5},"exclude_scoring_due_low_logistic":false,"loyalty_info":null,"template_tags":["Công dụng","Mùi hương","Dành cho da"],"has_template_tag":true,"sync_to_social_toggle":null,"sip_info":{"is_oversea":false,"origin_region":"vn"},"is_repeated_purchase":false,"display_variation_filter":null,"overall_fit":0,"is_normal_item":true,"viewed":null,"show_view":null,"sync_to_social_detail":null,"profile":null,"size_info_tags":null,"size_info_abt":"","image_data":[{"image_id":"vn-11134103-22120-68ixdb6abflv04","cover_image_id":"vn-11134103-22120-68ixdb6abflv04"},{"image_id":"vn-11134103-22120-6jke65abbflv01","cover_image_id":"vn-11134103-22120-6jke65abbflv01"},{"image_id":"vn-11134103-22120-xdaoi8kbbflvc2","cover_image_id":"vn-11134103-22120-xdaoi8kbbflvc2"},{"image_id":"vn-11134103-22120-d7ieshpbbflv16","cover_image_id":"vn-11134103-22120-d7ieshpbbflv16"},{"image_id":"vn-11134103-22120-xxt93qvbbflve6","cover_image_id":"vn-11134103-22120-xxt93qvbbflve6"}],"key_media":{"key_media_code":0,"key_media_id":""}},{"orderid":122144795261380,"itemid":17839269862,"cmtid":10095598004,"ctime":1668781200,"rating":1,"userid":45135554,"shopid":494676223,"comment":"Nhiều lần mua ở shop giao hàng nhanh nhưng đóng gói quá sơ sài k","rating_star":5,"status":2,"mtime":1668781200,"editable":0,"opt":2,"filter":7,"mentioned":null,"is_hidden":false,"author_username":"thuthao15042001","author_portrait":"0e49899303dc62c166f7dd578b583dbf","author_shopid":45134168,"anonymous":false,"images":["vn-11134103-22110-xlokfkzwq2jvb1"],"videos":[{"id":"vn_82371ce7-2814-4905-acd1-6a45c86121ba_000209","cover":"https://img.sp.mms.shopee.sg/vn-11110103-22110-hxewlj8wq2jv6f","url":"https://play-ws.vod.shopee.com/c3/98934353/103/A3oxONMCAGgLciwSEY4AACY.mp4","duration":26684,"upload_time":null,"mms_ext":"{\"vid\":\"vn_82371ce7-2814-4905-acd1-6a45c86121ba_000209\",\"biz\":103,\"duration\":26683,\"create_time\":1668781196,\"serviceID\":2,\"cover\":\"https://img.sp.mms.shopee.sg/vn-11110103-22110-hxewlj8wq2jv6f\",\"cover_list\":null,\"formats\":[{\"format\":1600005,\"defn\":\"V640P\",\"profile\":\"MP4\",\"path\":\"\",\"url\":\"http://play-ws.vod.shopee.com/c3/98934353/103/A3oxONMCAGgLciwSEY4AACY.mp4\",\"width\":576,\"height\":1024,\"bitrate\":739007,\"size\":2648609,\"fps\":25.03748,\"duration\":26680,\"update_time\":1668781212},{\"format\":1600046,\"defn\":\"V480P\",\"profile\":\"MP4\",\"path\":\"\",\"url\":\"http://play-ws.vod.shopee.com/c3/98934353/103/A3oxOLIIAFjfcSwSEZAKACY.mp4\",\"width\":480,\"height\":854,\"bitrate\":568615,\"size\":2238599,\"fps\":25.03748,\"duration\":26687,\"update_time\":1668781209}],\"default_format\":{\"format\":600001,\"defn\":\"ORI\",\"profile\":\"MP4\",\"path\":\"\",\"url\":\"http://play-ws.vod.shopee.com/api/v4/11110103/mms/vn_82371ce7-2814-4905-acd1-6a45c86121ba_000209.ori.mp4\",\"width\":576,\"height\":1024,\"bitrate\":1785481,\"size\":6414838,\"fps\":55.46964,\"duration\":26683,\"update_time\":1668781198},\"extend_formats\":{},\"ab_test\":\"\"}","cover_image_id":""}],"product_items":[{"itemid":17839269862,"shopid":494676223,"name":"Serum Mụn SKINTIFIC Chính Hãng Rulya Anti Acne 20ml","image":"2b53ac82ad54eff1c131b77f58a624dd","is_snapshot":1,"snapshotid":4005621971,"modelid":135025837391,"model_name":"","options":[""]}],"delete_reason":null,"delete_operator":null,"ItemRatingReply":null,"tags":null,"editable_date":null,"show_reply":null,"like_count":null,"liked":null,"sync_to_social":false,"detailed_rating":{"product_quality":5,"seller_service":5,"delivery_service":5},"exclude_scoring_due_low_logistic":false,"loyalty_info":null,"template_tags":null,"has_template_tag":false,"sync_to_social_toggle":null,"sip_info":{"is_oversea":false,"origin_region":"vn"},"is_repeated_purchase":false,"display_variation_filter":null,"overall_fit":0,"is_normal_item":true,"viewed":null,"show_view":null,"sync_to_social_detail":null,"profile":null,"size_info_tags":null,"size_info_abt":"","image_data":[{"image_id":"vn-11134103-22110-xlokfkzwq2jvb1","cover_image_id":"vn-11134103-22110-xlokfkzwq2jvb1"}],"key_media":{"key_media_code":0,"key_media_id":""}},{"orderid":121798933128405,"itemid":17839269862,"cmtid":10128956399,"ctime":1669127451,"rating":1,"userid":141542902,"shopid":494676223,"comment":"shop giao hàng nhanh \nserum dùng cảm giác lỏng hơn mấy lọ trước \nnên cho 4 sao nha","rating_star":4,"status":2,"mtime":1669127451,"editable":0,"opt":2,"filter":7,"mentioned":null,"is_hidden":false,"author_username":null,"author_portrait":null,"author_shopid":null,"anonymous":true,"images":["vn-11134103-22110-sal81j6rg8jvdc"],"videos":[{"id":"vn_04e134ed-c9ec-4234-9582-9ac146c656bd_000210","cover":"https://img.sp.mms.shopee.sg/vn-11110103-22110-hhel13jrg8jvd0","url":"https://play-ws.vod.shopee.com/c3/98934353/103/A3oxOIXsADhE934SEZQFACc.mp4","duration":15023,"upload_time":null,"mms_ext":"{\"vid\":\"vn_04e134ed-c9ec-4234-9582-9ac146c656bd_000210\",\"biz\":103,\"duration\":15023,\"create_time\":1669127323,\"serviceID\":2,\"cover\":\"https://img.sp.mms.shopee.sg/vn-11110103-22110-hhel13jrg8jvd0\",\"cover_list\":null,\"formats\":[{\"format\":1600005,\"defn\":\"V640P\",\"profile\":\"MP4\",\"path\":\"\",\"url\":\"http://play-ws.vod.shopee.com/c3/98934353/103/A3oxOIXsADhE934SEZQFACc.mp4\",\"width\":656,\"height\":576,\"bitrate\":360196,\"size\":687986,\"fps\":25.06596,\"duration\":15159,\"update_time\":1669127328},{\"format\":1600046,\"defn\":\"V480P\",\"profile\":\"MP4\",\"path\":\"\",\"url\":\"http://play-ws.vod.shopee.com/c3/98934353/103/A3oxOBWxABRI934SEZMIACc.mp4\",\"width\":546,\"height\":480,\"bitrate\":333174,\"size\":636781,\"fps\":25.06596,\"duration\":15159,\"update_time\":1669127328}],\"default_format\":{\"format\":600001,\"defn\":\"ORI\",\"profile\":\"MP4\",\"path\":\"\",\"url\":\"http://play-ws.vod.shopee.com/api/v4/11110103/mms/vn_04e134ed-c9ec-4234-9582-9ac146c656bd_000210.ori.mp4\",\"width\":656,\"height\":576,\"bitrate\":737171,\"size\":1389569,\"fps\":24.06648,\"duration\":15023,\"update_time\":1669127324},\"extend_formats\":{},\"ab_test\":\"\"}","cover_image_id":""}],"product_items":[{"itemid":17839269862,"shopid":494676223,"name":"Serum Mụn SKINTIFIC Chính Hãng Rulya Anti Acne 20ml","image":"sg-11134201-22110-9ebzy6e3wpjvd8","is_snapshot":1,"snapshotid":3991167340,"modelid":135025837391,"model_name":"","options":[""]}],"delete_reason":null,"delete_operator":null,"ItemRatingReply":null,"tags":null,"editable_date":null,"show_reply":null,"like_count":null,"liked":null,"sync_to_social":false,"detailed_rating":{"product_quality":4,"seller_service":5,"delivery_service":5},"exclude_scoring_due_low_logistic":false,"loyalty_info":null,"template_tags":null,"has_template_tag":false,"sync_to_social_toggle":null,"sip_info":{"is_oversea":false,"origin_region":"vn"},"is_repeated_purchase":false,"display_variation_filter":null,"overall_fit":0,"is_normal_item":true,"viewed":null,"show_view":null,"sync_to_social_detail":null,"profile":null,"size_info_tags":null,"size_info_abt":"","image_data":[{"image_id":"vn-11134103-22110-sal81j6rg8jvdc","cover_image_id":"vn-11134103-22110-sal81j6rg8jvdc"}],"key_media":{"key_media_code":0,"key_media_id":""}},{"orderid":124857961261084,"itemid":17839269862,"cmtid":10347460408,"ctime":1671374235,"rating":1,"userid":75387273,"shopid":494676223,"comment":"Công dụng:trị mụn\nMùi hương:thơm\nDành cho da:mụn\n\nShipper thân thiện, ship hàng nhanh. Cảm ơn shop","rating_star":5,"status":2,"mtime":1671374235,"editable":1,"opt":2,"filter":7,"mentioned":null,"is_hidden":false,"author_username":"tranthuytrang07012002","author_portrait":"e7e13f1f12d3c4dc6062f3075e8ec6c6","author_shopid":75385803,"anonymous":false,"images":["vn-11134103-22120-ko3851xyk9kv1b","vn-11134103-22120-ozpg2b4yk9kvc3","vn-11134103-22120-29ksqtizk9kvcb","vn-11134103-22120-tal8oqqzk9kvbc","vn-11134103-22120-h2ht5gwzk9kv32"],"videos":[{"id":"vn_603e6ffd-a0d7-4b05-8106-33513b4285e3_000218","cover":"https://img.sp.mms.shopee.sg/vn-11110103-22120-2k3hj2a1k9kv6d","url":"https://play-ws.vod.shopee.com/api/v4/11110103/mms/vn_603e6ffd-a0d7-4b05-8106-33513b4285e3_000218.16000051671374233.mp4","duration":5822,"upload_time":null,"mms_ext":"{\"vid\":\"vn_603e6ffd-a0d7-4b05-8106-33513b4285e3_000218\",\"biz\":103,\"duration\":5791,\"create_time\":1671374233,\"serviceID\":2,\"cover\":\"https://img.sp.mms.shopee.sg/vn-11110103-22120-2k3hj2a1k9kv6d\",\"cover_list\":null,\"formats\":[{\"format\":1600005,\"defn\":\"V640P\",\"profile\":\"MP4\",\"path\":\"\",\"url\":\"http://play-ws.vod.shopee.com/api/v4/11110103/mms/vn_603e6ffd-a0d7-4b05-8106-33513b4285e3_000218.16000051671374233.mp4\",\"width\":544,\"height\":960,\"bitrate\":450575,\"size\":405381,\"fps\":25.17123,\"duration\":5840,\"update_time\":1671374235},{\"format\":1600046,\"defn\":\"V480P\",\"profile\":\"MP4\",\"path\":\"\",\"url\":\"http://play-ws.vod.shopee.com/api/v4/11110103/mms/vn_603e6ffd-a0d7-4b05-8106-33513b4285e3_000218.16000461671374234.mp4\",\"width\":480,\"height\":848,\"bitrate\":394168,\"size\":363950,\"fps\":25.17123,\"duration\":5840,\"update_time\":1671374239}],\"default_format\":{\"format\":600001,\"defn\":\"ORI\",\"profile\":\"MP4\",\"path\":\"\",\"url\":\"http://play-ws.vod.shopee.com/api/v4/11110103/mms/vn_603e6ffd-a0d7-4b05-8106-33513b4285e3_000218.ori.mp4\",\"width\":544,\"height\":960,\"bitrate\":5014314,\"size\":3729508,\"fps\":29.86913,\"duration\":5791,\"update_time\":1671374234},\"extend_formats\":{},\"ab_test\":\"\"}","cover_image_id":""}],"product_items":[{"itemid":17839269862,"shopid":494676223,"name":"Serum Mụn SKINTIFIC Chính Hãng Rulya Anti Acne 20ml","image":"sg-11134201-22120-1k3lkog7aykve3","is_snapshot":1,"snapshotid":6200086858,"modelid":135025837391,"model_name":"","options":[""]}],"delete_reason":null,"delete_operator":null,"ItemRatingReply":null,"tags":null,"editable_date":1673966235,"show_reply":null,"like_count":null,"liked":null,"sync_to_social":false,"detailed_rating":{"product_quality":5,"seller_service":5,"delivery_service":5},"exclude_scoring_due_low_logistic":false,"loyalty_info":null,"template_tags":["Công dụng","Mùi hương","Dành cho da"],"has_template_tag":true,"sync_to_social_toggle":null,"sip_info":{"is_oversea":false,"origin_region":"vn"},"is_repeated_purchase":false,"display_variation_filter":null,"overall_fit":0,"is_normal_item":true,"viewed":null,"show_view":null,"sync_to_social_detail":null,"profile":null,"size_info_tags":null,"size_info_abt":"","image_data":[{"image_id":"vn-11134103-22120-ko3851xyk9kv1b","cover_image_id":"vn-11134103-22120-ko3851xyk9kv1b"},{"image_id":"vn-11134103-22120-ozpg2b4yk9kvc3","cover_image_id":"vn-11134103-22120-ozpg2b4yk9kvc3"},{"image_id":"vn-11134103-22120-29ksqtizk9kvcb","cover_image_id":"vn-11134103-22120-29ksqtizk9kvcb"},{"image_id":"vn-11134103-22120-tal8oqqzk9kvbc","cover_image_id":"vn-11134103-22120-tal8oqqzk9kvbc"},{"image_id":"vn-11134103-22120-h2ht5gwzk9kv32","cover_image_id":"vn-11134103-22120-h2ht5gwzk9kv32"}],"key_media":{"key_media_code":0,"key_media_id":""}},{"orderid":125773574289803,"itemid":17839269862,"cmtid":10433950167,"ctime":1672332470,"rating":1,"userid":47775997,"shopid":494676223,"comment":"hàng tốt, đúng như mẫu. hình ảnh và video mang tính chất nhận xuuu","rating_star":5,"status":2,"mtime":1672332470,"editable":1,"opt":2,"filter":7,"mentioned":null,"is_hidden":false,"author_username":"k*****2","author_portrait":"fb34192fbbe273a2874a0589b792529c","author_shopid":47774610,"anonymous":true,"images":["vn-11134103-22120-fvm4io9ueolvf8"],"videos":[{"id":"vn_9828213c-9ae8-4a34-8cfc-e9ce864a7efc_000221","cover":"https://img.sp.mms.shopee.sg/vn-11110103-22120-kwsh9jeveolv05","url":"https://play-ws.vod.shopee.com/api/v4/11110103/mms/vn_9828213c-9ae8-4a34-8cfc-e9ce864a7efc_000221.16000051672332466.mp4","duration":4598,"upload_time":null,"mms_ext":"{\"vid\":\"vn_9828213c-9ae8-4a34-8cfc-e9ce864a7efc_000221\",\"biz\":103,\"duration\":4625,\"create_time\":1672332466,\"serviceID\":2,\"cover\":\"https://img.sp.mms.shopee.sg/vn-11110103-22120-kwsh9jeveolv05\",\"cover_list\":null,\"formats\":[{\"format\":1600005,\"defn\":\"V640P\",\"profile\":\"MP4\",\"path\":\"\",\"url\":\"http://play-ws.vod.shopee.com/api/v4/11110103/mms/vn_9828213c-9ae8-4a34-8cfc-e9ce864a7efc_000221.16000051672332466.mp4\",\"width\":358,\"height\":640,\"bitrate\":265306,\"size\":213640,\"fps\":25.21739,\"duration\":4599,\"update_time\":1672332468}],\"default_format\":{\"format\":600001,\"defn\":\"ORI\",\"profile\":\"MP4\",\"path\":\"\",\"url\":\"http://play-ws.vod.shopee.com/api/v4/11110103/mms/vn_9828213c-9ae8-4a34-8cfc-e9ce864a7efc_000221.ori.mp4\",\"width\":358,\"height\":640,\"bitrate\":1659520,\"size\":1034255,\"fps\":24,\"duration\":4625,\"update_time\":1672332467},\"extend_formats\":{},\"ab_test\":\"\"}","cover_image_id":""}],"product_items":[{"itemid":17839269862,"shopid":494676223,"name":"Serum Mụn SKINTIFIC Chính Hãng Rulya Anti Acne 20ml","image":"sg-11134201-22120-s2pjsld2zelv59","is_snapshot":1,"snapshotid":8900436952,"modelid":135025837391,"model_name":"","options":[""]}],"delete_reason":null,"delete_operator":null,"ItemRatingReply":null,"tags":null,"editable_date":1674924470,"show_reply":null,"like_count":null,"liked":null,"sync_to_social":false,"detailed_rating":{"product_quality":5,"seller_service":5,"delivery_service":5},"exclude_scoring_due_low_logistic":false,"loyalty_info":null,"template_tags":null,"has_template_tag":false,"sync_to_social_toggle":null,"sip_info":{"is_oversea":false,"origin_region":"vn"},"is_repeated_purchase":false,"display_variation_filter":null,"overall_fit":0,"is_normal_item":true,"viewed":null,"show_view":null,"sync_to_social_detail":null,"profile":null,"size_info_tags":null,"size_info_abt":"","image_data":[{"image_id":"vn-11134103-22120-fvm4io9ueolvf8","cover_image_id":"vn-11134103-22120-fvm4io9ueolvf8"}],"key_media":{"key_media_code":0,"key_media_id":""}},{"orderid":108478759665563,"itemid":17839269862,"cmtid":8777121317,"ctime":1656138642,"rating":1,"userid":169876467,"shopid":494676223,"comment":"Hàng rất tốt sẽ mãi ủng hộ hình ảnh mang tính chất nhận xuu thôi nhé🤍","rating_star":5,"status":2,"mtime":1656138642,"editable":0,"opt":2,"filter":7,"mentioned":null,"is_hidden":false,"author_username":"nguyenhan2007haha","author_portrait":"805d6009ffff42a70d7a7369b7f97b5e","author_shopid":169874126,"anonymous":false,"images":["vn-11134103-22060-g6olm9rcw9dvfc"],"videos":[{"id":"vn_dbc7eccc-b4d0-44c4-8541-80c7ee5b6598_000163","cover":"https://img.sp.mms.shopee.sg/vn-11110103-22120-gx3at225h3kv1f","url":"https://play-aka.vod.shopee.com/c3/98934353/103/Anoyr7EAMB85ZgYhJAIFAEc.mp4","duration":4066,"upload_time":null,"mms_ext":"{\"vid\":\"vn_dbc7eccc-b4d0-44c4-8541-80c7ee5b6598_000163\",\"biz\":103,\"duration\":4083,\"create_time\":1656138639,\"serviceID\":3,\"cover\":\"https://img.sp.mms.shopee.sg/vn-11110103-22120-gx3at225h3kv1f\",\"cover_list\":null,\"formats\":[{\"format\":1600005,\"defn\":\"V640P\",\"profile\":\"MP4\",\"path\":\"\",\"url\":\"http://play-aka.vod.shopee.com/c3/98934353/103/Anoyr7EAMB85ZgYhJAIFAEc.mp4\",\"width\":640,\"height\":360,\"bitrate\":969007,\"size\":495731,\"fps\":25,\"duration\":4079,\"update_time\":1656138647}],\"default_format\":{\"format\":600001,\"defn\":\"ORI\",\"profile\":\"MP4\",\"path\":\"\",\"url\":\"http://play-aka.vod.shopee.com/c3/98934353/103/AnoyS3YAPLU4ZgYhMwIFAEc.mp4\",\"width\":640,\"height\":360,\"bitrate\":1580379,\"size\":808127,\"fps\":24,\"duration\":4083,\"update_time\":1656138640},\"extend_formats\":{},\"ab_test\":\"\"}","cover_image_id":""}],"product_items":[{"itemid":17839269862,"shopid":494676223,"name":"Serum Mụn SKINTIFIC Chính Hãng Rulya Anti Acne 20ml","image":"afd17f8a1920780ccd39a6dbb9e6f358","is_snapshot":1,"snapshotid":3586186869,"modelid":135025837391,"model_name":"","options":[""]}],"delete_reason":null,"delete_operator":null,"ItemRatingReply":{"orderid":108478759665563,"itemid":null,"cmtid":8777121317,"ctime":1656305601,"rating":null,"userid":494695801,"shopid":null,"comment":"SKINTIFIC cảm ơn bạn đã tin tưởng và ủng hộ! Nếu bạn có bất cứ vấn đề gì đều có thể nhắn tin với SKINTIFIC để có được giải đáp tận tình nhất. SKINTIFIC rất sẵn lòng được phục vụ bạn!","rating_star":null,"status":null,"mtime":1656305601,"editable":null,"opt":null,"filter":null,"mentioned":null,"is_hidden":false},"tags":null,"editable_date":1658730642,"show_reply":null,"like_count":null,"liked":null,"sync_to_social":false,"detailed_rating":{"product_quality":5,"seller_service":null,"delivery_service":null},"exclude_scoring_due_low_logistic":false,"loyalty_info":null,"template_tags":null,"has_template_tag":false,"sync_to_social_toggle":null,"sip_info":{"is_oversea":false,"origin_region":"vn"},"is_repeated_purchase":false,"display_variation_filter":null,"overall_fit":0,"is_normal_item":true,"viewed":null,"show_view":null,"sync_to_social_detail":null,"profile":null,"size_info_tags":null,"size_info_abt":"","image_data":[{"image_id":"vn-11134103-22060-g6olm9rcw9dvfc","cover_image_id":"vn-11134103-22060-g6olm9rcw9dvfc"}],"key_media":{"key_media_code":0,"key_media_id":""}},{"orderid":124800985158517,"itemid":17839269862,"cmtid":10391550306,"ctime":1671846483,"rating":1,"userid":483756249,"shopid":494676223,"comment":"K is the one who wants it for me and the kids will have a good day at work today so we will","rating_star":5,"status":2,"mtime":1671846483,"editable":1,"opt":2,"filter":7,"mentioned":null,"is_hidden":false,"author_username":"nano211221","author_portrait":"556b8552c6ab10888060095dc3d724ba","author_shopid":483736671,"anonymous":false,"images":["vn-11134103-22120-emtj9sztdglvf4"],"videos":[{"id":"vn_f31934d7-eb58-4da7-91a4-010832c84254_000219","cover":"https://play-ws.vod.shopee.com/vn_f31934d7-eb58-4da7-91a4-010832c84254_000219.ori.jpg","url":"https://play-ws.vod.shopee.com/vn_f31934d7-eb58-4da7-91a4-010832c84254_000219.ori.mp4","duration":4316,"upload_time":null,"mms_ext":null,"cover_image_id":""}],"product_items":[{"itemid":17839269862,"shopid":494676223,"name":"Serum Mụn SKINTIFIC Chính Hãng Rulya Anti Acne 20ml","image":"sg-11134201-22120-1k3lkog7aykve3","is_snapshot":1,"snapshotid":6200086858,"modelid":135025837391,"model_name":"","options":[""]}],"delete_reason":null,"delete_operator":null,"ItemRatingReply":null,"tags":null,"editable_date":1674438483,"show_reply":null,"like_count":null,"liked":null,"sync_to_social":false,"detailed_rating":{"product_quality":5,"seller_service":5,"delivery_service":5},"exclude_scoring_due_low_logistic":false,"loyalty_info":null,"template_tags":null,"has_template_tag":false,"sync_to_social_toggle":null,"sip_info":{"is_oversea":false,"origin_region":"vn"},"is_repeated_purchase":false,"display_variation_filter":null,"overall_fit":0,"is_normal_item":true,"viewed":null,"show_view":null,"sync_to_social_detail":null,"profile":null,"size_info_tags":null,"size_info_abt":"","image_data":[{"image_id":"vn-11134103-22120-emtj9sztdglvf4","cover_image_id":"vn-11134103-22120-emtj9sztdglvf4"}],"key_media":{"key_media_code":0,"key_media_id":""}},{"orderid":107768630265891,"itemid":17839269862,"cmtid":8689307948,"ctime":1655346170,"rating":1,"userid":122404768,"shopid":494676223,"comment":"Công dụng:hỖ trợ trị mụn\nMùi hương:k mùi\nDành cho da:da khô\n\nChuẩn bị hàng hơi lâu, chất lượng sp tốt","rating_star":5,"status":2,"mtime":1655346170,"editable":0,"opt":2,"filter":7,"mentioned":null,"is_hidden":false,"author_username":"huyen12072001","author_portrait":"65a18fce2c2f90e9de7a9c3cf10602d0","author_shopid":122402944,"anonymous":false,"images":["vn-11134103-22060-wtuykdj2svdvbb"],"videos":[{"id":"vn_b684f6af-462f-406c-a2ec-5fbf1e9a1651_000160","cover":"https://play-ws.vod.shopee.com/c3/98934353/103/AnoyiAcASONFqQUhSgIKAEc.jpg","url":"https://play-ws.vod.shopee.com/c3/98934353/103/Anoyx5MAtFtGqQUhEAIMAEc.mp4","duration":6333,"upload_time":null,"mms_ext":"{\"vid\":\"vn_b684f6af-462f-406c-a2ec-5fbf1e9a1651_000160\",\"biz\":103,\"duration\":6360,\"create_time\":1655346131,\"serviceID\":2,\"cover\":\"http://play-ws.vod.shopee.com/c3/98934353/103/AnoyiAcASONFqQUhSgIKAEc.jpg\",\"cover_list\":null,\"formats\":[{\"format\":1600005,\"defn\":\"V640P\",\"profile\":\"MP4\",\"path\":\"\",\"url\":\"http://play-ws.vod.shopee.com/c3/98934353/103/Anoyx5MAtFtGqQUhEAIMAEc.mp4\",\"width\":360,\"height\":640,\"bitrate\":898820,\"size\":722464,\"fps\":25,\"duration\":6360,\"update_time\":1655346140}],\"default_format\":{\"format\":600001,\"defn\":\"ORI\",\"profile\":\"MP4\",\"path\":\"\",\"url\":\"http://play-ws.vod.shopee.com/c3/98934353/103/Anoymv8AOOVFqQUhQAIIAEY.mp4\",\"width\":360,\"height\":640,\"bitrate\":1587607,\"size\":1262322,\"fps\":24,\"duration\":6333,\"update_time\":1655346133},\"extend_formats\":{},\"ab_test\":\"\"}","cover_image_id":""}],"product_items":[{"itemid":17839269862,"shopid":494676223,"name":"Serum Mụn SKINTIFIC Chính Hãng Rulya Anti Acne 20ml","image":"afd17f8a1920780ccd39a6dbb9e6f358","is_snapshot":1,"snapshotid":3558368908,"modelid":135025837391,"model_name":"","options":[""]}],"delete_reason":null,"delete_operator":null,"ItemRatingReply":{"orderid":107768630265891,"itemid":null,"cmtid":8689307948,"ctime":1655438183,"rating":null,"userid":494695801,"shopid":null,"comment":"SKINTIFIC cảm ơn bạn đã tin tưởng và ủng hộ! Nếu bạn có bất cứ vấn đề gì đều có thể nhắn tin với SKINTIFIC để có được giải đáp tận tình nhất. SKINTIFIC rất sẵn lòng được phục vụ bạn!","rating_star":null,"status":null,"mtime":1655438183,"editable":null,"opt":null,"filter":null,"mentioned":null,"is_hidden":false},"tags":null,"editable_date":1657938170,"show_reply":null,"like_count":null,"liked":null,"sync_to_social":false,"detailed_rating":{"product_quality":5,"seller_service":null,"delivery_service":null},"exclude_scoring_due_low_logistic":false,"loyalty_info":null,"template_tags":["Công dụng","Mùi hương","Dành cho da"],"has_template_tag":true,"sync_to_social_toggle":null,"sip_info":{"is_oversea":false,"origin_region":"vn"},"is_repeated_purchase":false,"display_variation_filter":null,"overall_fit":0,"is_normal_item":true,"viewed":null,"show_view":null,"sync_to_social_detail":null,"profile":null,"size_info_tags":null,"size_info_abt":"","image_data":[{"image_id":"vn-11134103-22060-wtuykdj2svdvbb","cover_image_id":"vn-11134103-22060-wtuykdj2svdvbb"}],"key_media":{"key_media_code":0,"key_media_id":""}},{"orderid":108129439288254,"itemid":17839269862,"cmtid":8748387949,"ctime":1655884072,"rating":1,"userid":664517003,"shopid":494676223,"comment":"Giao hàng nhanh, đóng gói kĩ, chất lượng sản phẩm tốt, nên sử dụng","rating_star":5,"status":2,"mtime":1655884072,"editable":0,"opt":2,"filter":7,"mentioned":null,"is_hidden":false,"author_username":"y*****1","author_portrait":"","author_shopid":664497418,"anonymous":true,"images":["vn-11134103-22060-d7759akyo5dvfc"],"videos":[{"id":"vn_596b3ca5-c79d-4395-878a-4f0583927331_000162","cover":"https://play-ws.vod.shopee.com/c3/98934353/103/AnoynLQAML2GKQYhRQIHAEc.jpg","url":"https://play-ws.vod.shopee.com/c3/98934353/103/AnoyJBUAJBOHKQYhQAINAEc.mp4","duration":7806,"upload_time":null,"mms_ext":"{\"vid\":\"vn_596b3ca5-c79d-4395-878a-4f0583927331_000162\",\"biz\":103,\"duration\":7880,\"create_time\":1655884065,\"serviceID\":2,\"cover\":\"http://play-ws.vod.shopee.com/c3/98934353/103/AnoynLQAML2GKQYhRQIHAEc.jpg\",\"cover_list\":null,\"formats\":[{\"format\":1600005,\"defn\":\"V640P\",\"profile\":\"MP4\",\"path\":\"\",\"url\":\"http://play-ws.vod.shopee.com/c3/98934353/103/AnoyJBUAJBOHKQYhQAINAEc.mp4\",\"width\":360,\"height\":640,\"bitrate\":822411,\"size\":864714,\"fps\":25,\"duration\":7880,\"update_time\":1655884072}],\"default_format\":{\"format\":600001,\"defn\":\"ORI\",\"profile\":\"MP4\",\"path\":\"\",\"url\":\"http://play-ws.vod.shopee.com/c3/98934353/103/Anoyle0A=L6GKQYhJgIEAEY.mp4\",\"width\":360,\"height\":640,\"bitrate\":1550085,\"size\":1646014,\"fps\":24,\"duration\":7833,\"update_time\":1655884066},\"extend_formats\":{},\"ab_test\":\"\"}","cover_image_id":""}],"product_items":[{"itemid":17839269862,"shopid":494676223,"name":"Serum Mụn SKINTIFIC Chính Hãng Rulya Anti Acne 20ml","image":"afd17f8a1920780ccd39a6dbb9e6f358","is_snapshot":1,"snapshotid":3573694431,"modelid":135025837391,"model_name":"","options":[""]}],"delete_reason":null,"delete_operator":null,"ItemRatingReply":{"orderid":108129439288254,"itemid":null,"cmtid":8748387949,"ctime":1655974558,"rating":null,"userid":494695801,"shopid":null,"comment":"SKINTIFIC cảm ơn bạn đã tin tưởng và ủng hộ! Nếu bạn có bất cứ vấn đề gì đều có thể nhắn tin với SKINTIFIC để có được giải đáp tận tình nhất. SKINTIFIC rất sẵn lòng được phục vụ bạn!","rating_star":null,"status":null,"mtime":1655974558,"editable":null,"opt":null,"filter":null,"mentioned":null,"is_hidden":false},"tags":null,"editable_date":1658476072,"show_reply":null,"like_count":null,"liked":null,"sync_to_social":false,"detailed_rating":{"product_quality":5,"seller_service":null,"delivery_service":null},"exclude_scoring_due_low_logistic":false,"loyalty_info":null,"template_tags":null,"has_template_tag":false,"sync_to_social_toggle":null,"sip_info":{"is_oversea":false,"origin_region":"vn"},"is_repeated_purchase":false,"display_variation_filter":null,"overall_fit":0,"is_normal_item":true,"viewed":null,"show_view":null,"sync_to_social_detail":null,"profile":null,"size_info_tags":null,"size_info_abt":"","image_data":[{"image_id":"vn-11134103-22060-d7759akyo5dvfc","cover_image_id":"vn-11134103-22060-d7759akyo5dvfc"}],"key_media":{"key_media_code":0,"key_media_id":""}},{"orderid":108206772332099,"itemid":17839269862,"cmtid":8653396304,"ctime":1655023921,"rating":1,"userid":517843588,"shopid":494676223,"comment":"Công dụng:trị mụn\nMùi hương:kh có\nDành cho da:tất cả\n\ntuyệt vời kzmjznzkLLaKzknznznxnxnmsmznznnz","rating_star":5,"status":2,"mtime":1655023921,"editable":0,"opt":2,"filter":7,"mentioned":null,"is_hidden":false,"author_username":"v*****8","author_portrait":"289433f2405898d4a7640c270fdd8e1e","author_shopid":517824009,"anonymous":true,"images":["vn-11134103-22060-y07y2dgehqdv78"],"videos":[{"id":"vn_894ba13a-9b27-4147-93a8-71b469f14712_000159","cover":"https://play-ws.vod.shopee.com/c3/98934353/103/Anoyl=UAgHdyXAUhBwIPAEc.jpg","url":"https://play-ws.vod.shopee.com/c3/98934353/103/Anoy=6AAGElzXAUhHwIDAEY.mp4","duration":19782,"upload_time":null,"mms_ext":"{\"vid\":\"vn_894ba13a-9b27-4147-93a8-71b469f14712_000159\",\"biz\":103,\"duration\":19959,\"create_time\":1655023902,\"serviceID\":6,\"cover\":\"http://play-ws.vod.shopee.com/c3/98934353/103/Anoyl=UAgHdyXAUhBwIPAEc.jpg\",\"cover_list\":null,\"formats\":[{\"format\":1600005,\"defn\":\"V640P\",\"profile\":\"MP4\",\"path\":\"\",\"url\":\"http://play-ws.vod.shopee.com/c3/98934353/103/Anoy=6AAGElzXAUhHwIDAEY.mp4\",\"width\":576,\"height\":1024,\"bitrate\":749136,\"size\":1998607,\"fps\":25.0501,\"duration\":19959,\"update_time\":1655023915}],\"default_format\":{\"format\":600001,\"defn\":\"ORI\",\"profile\":\"MP4\",\"path\":\"\",\"url\":\"http://play-ws.vod.shopee.com/c3/98934353/103/AnoyXBgAsHFyXAUhEgINAEY.mp4\",\"width\":576,\"height\":1024,\"bitrate\":1227127,\"size\":3370301,\"fps\":24.05053,\"duration\":19782,\"update_time\":1655023903},\"extend_formats\":{},\"ab_test\":\"\"}","cover_image_id":""}],"product_items":[{"itemid":17839269862,"shopid":494676223,"name":"Serum Mụn SKINTIFIC Chính Hãng Rulya Anti Acne 20ml","image":"afd17f8a1920780ccd39a6dbb9e6f358","is_snapshot":1,"snapshotid":3573694431,"modelid":135025837391,"model_name":"","options":[""]}],"delete_reason":null,"delete_operator":null,"ItemRatingReply":{"orderid":108206772332099,"itemid":null,"cmtid":8653396304,"ctime":1655104132,"rating":null,"userid":494695801,"shopid":null,"comment":"SKINTIFIC cảm ơn bạn đã tin tưởng và ủng hộ! Nếu bạn có bất cứ vấn đề gì đều có thể nhắn tin với SKINTIFIC để có được giải đáp tận tình nhất. SKINTIFIC rất sẵn lòng được phục vụ bạn!","rating_star":null,"status":null,"mtime":1655104132,"editable":null,"opt":null,"filter":null,"mentioned":null,"is_hidden":false},"tags":[{"tag_id":2,"tag_description":"Chất lượng sản phẩm tuyệt vời"},{"tag_id":5,"tag_description":"Đóng gói sản phẩm rất đẹp và chắc chắn"}],"editable_date":1657615921,"show_reply":null,"like_count":null,"liked":null,"sync_to_social":false,"detailed_rating":{"product_quality":5,"seller_service":null,"delivery_service":null},"exclude_scoring_due_low_logistic":false,"loyalty_info":null,"template_tags":["Công dụng","Mùi hương","Dành cho da"],"has_template_tag":true,"sync_to_social_toggle":null,"sip_info":{"is_oversea":false,"origin_region":"vn"},"is_repeated_purchase":false,"display_variation_filter":null,"overall_fit":0,"is_normal_item":true,"viewed":null,"show_view":null,"sync_to_social_detail":null,"profile":null,"size_info_tags":null,"size_info_abt":"","image_data":[{"image_id":"vn-11134103-22060-y07y2dgehqdv78","cover_image_id":"vn-11134103-22060-y07y2dgehqdv78"}],"key_media":{"key_media_code":0,"key_media_id":""}},{"orderid":104563703349639,"itemid":17839269862,"cmtid":8554507379,"ctime":1654185772,"rating":1,"userid":502897633,"shopid":494676223,"comment":"Công dụng:trị mụn\nMùi hương:không mùi\nDành cho da:da dầu\n\nkhông biết do sản phẩm đẩy mụn hay do mình không hợp mà khi dùng mình bị lên khá nhiều mụn ẩn liti và mụn viêm","rating_star":5,"status":2,"mtime":1654185772,"editable":0,"opt":2,"filter":7,"mentioned":null,"is_hidden":false,"author_username":"m*****3","author_portrait":"","author_shopid":502878055,"anonymous":true,"images":["vn-11134103-22060-4vtt5tfxmcdv22"],"videos":[{"id":"vn_22eaa8b2-e0e0-49fa-bb8b-8e11264b43e0_000155","cover":"https://vod.sp-cdn.shopee.com/c3/98934353/103/AnoyOUkA8IealAQhDgIGAEc.jpg","url":"https://vod.sp-cdn.shopee.com/c3/98934353/103/AnoyujMATPOalAQhAgIHAEY.mp4","duration":17413,"upload_time":null,"mms_ext":"{\"vid\":\"vn_22eaa8b2-e0e0-49fa-bb8b-8e11264b43e0_000155\",\"biz\":103,\"duration\":17415,\"create_time\":1654185696,\"serviceID\":2,\"cover\":\"http://vod.sp-cdn.shopee.com/c3/98934353/103/AnoyOUkA8IealAQhDgIGAEc.jpg\",\"cover_list\":null,\"formats\":[{\"format\":1600005,\"defn\":\"V640P\",\"profile\":\"MP4\",\"path\":\"\",\"url\":\"http://vod.sp-cdn.shopee.com/c3/98934353/103/AnoyujMATPOalAQhAgIHAEY.mp4\",\"width\":576,\"height\":1024,\"bitrate\":761202,\"size\":1753780,\"fps\":25,\"duration\":17415,\"update_time\":1654185704}],\"default_format\":{\"format\":600001,\"defn\":\"ORI\",\"profile\":\"MP4\",\"path\":\"\",\"url\":\"http://vod.sp-cdn.shopee.com/c3/98934353/103/AnoyFiwAOIqalAQhQwIGAEY.mp4\",\"width\":576,\"height\":1024,\"bitrate\":1091406,\"size\":2671964,\"fps\":24.0621,\"duration\":17412,\"update_time\":1654185697},\"extend_formats\":{},\"ab_test\":\"\"}","cover_image_id":""}],"product_items":[{"itemid":17839269862,"shopid":494676223,"name":"Serum Mụn SKINTIFIC Chính Hãng Rulya Anti Acne 20ml","image":"afd17f8a1920780ccd39a6dbb9e6f358","is_snapshot":1,"snapshotid":3485747263,"modelid":135025837391,"model_name":"","options":[""]}],"delete_reason":null,"delete_operator":null,"ItemRatingReply":{"orderid":104563703349639,"itemid":null,"cmtid":8554507379,"ctime":1654935815,"rating":null,"userid":494695801,"shopid":null,"comment":"SKINTIFIC cảm ơn bạn đã tin tưởng và ủng hộ! Nếu bạn có bất cứ vấn đề gì đều có thể nhắn tin với SKINTIFIC để có được giải đáp tận tình nhất. SKINTIFIC rất sẵn lòng được phục vụ bạn!","rating_star":null,"status":null,"mtime":1654935815,"editable":null,"opt":null,"filter":null,"mentioned":null,"is_hidden":false},"tags":null,"editable_date":1656777772,"show_reply":null,"like_count":null,"liked":null,"sync_to_social":false,"detailed_rating":{"product_quality":5,"seller_service":null,"delivery_service":null},"exclude_scoring_due_low_logistic":false,"loyalty_info":null,"template_tags":["Công dụng","Mùi hương","Dành cho da"],"has_template_tag":true,"sync_to_social_toggle":null,"sip_info":{"is_oversea":false,"origin_region":"vn"},"is_repeated_purchase":false,"display_variation_filter":null,"overall_fit":0,"is_normal_item":true,"viewed":null,"show_view":null,"sync_to_social_detail":null,"profile":null,"size_info_tags":null,"size_info_abt":"","image_data":[{"image_id":"vn-11134103-22060-4vtt5tfxmcdv22","cover_image_id":"vn-11134103-22060-4vtt5tfxmcdv22"}],"key_media":{"key_media_code":0,"key_media_id":""}},{"orderid":104161112360105,"itemid":17839269862,"cmtid":8185699489,"ctime":1650867514,"rating":1,"userid":19028440,"shopid":494676223,"comment":"Công dụng:trị mụn\nKhả năng thẩm thấu:chưa sdung\n\nĐể trải nghiệm 1 tgian mới rì viu đc. Giao nhanh","rating_star":5,"status":2,"mtime":1650867514,"editable":0,"opt":2,"filter":7,"mentioned":null,"is_hidden":false,"author_username":"levuphuonglinhsma","author_portrait":"addffb1d74ae8c71091bda83f3b8c63e","author_shopid":19027104,"anonymous":false,"images":["5f3165e659bc550997fe0d76f2cc436d"],"videos":[{"id":"vn_2fa99476-0e45-4dfd-8145-17621d1d8b96_000143","cover":"https://vod.sp-cdn.shopee.com/c3/98934353/103/AnoxDAwAMIZ6fQERFQgARw.jpg","url":"https://vod.sp-cdn.shopee.com/c3/98934353/103/Anox2dUAvBt7fQER=woARg.mp4","duration":9639,"upload_time":null,"mms_ext":"{\"vid\":\"vn_2fa99476-0e45-4dfd-8145-17621d1d8b96_000143\",\"biz\":103,\"duration\":9800,\"create_time\":1650867477,\"serviceID\":2,\"cover\":\"http://vod.sp-cdn.shopee.com/c3/98934353/103/AnoxDAwAMIZ6fQERFQgARw.jpg\",\"cover_list\":null,\"formats\":[{\"format\":1600005,\"defn\":\"V640P\",\"profile\":\"MP4\",\"path\":\"\",\"url\":\"http://vod.sp-cdn.shopee.com/c3/98934353/103/Anox2dUAvBt7fQER=woARg.mp4\",\"width\":640,\"height\":1138,\"bitrate\":862226,\"size\":1123335,\"fps\":25,\"duration\":9800,\"update_time\":1650867488}],\"default_format\":{\"format\":600001,\"defn\":\"ORI\",\"profile\":\"MP4\",\"path\":\"\",\"url\":\"http://vod.sp-cdn.shopee.com/c3/98934353/103/Anoxl6kAqIh6fQEReAYARg.mp4\",\"width\":720,\"height\":1280,\"bitrate\":1590886,\"size\":2041962,\"fps\":24.10345,\"duration\":9638,\"update_time\":1650867479},\"extend_formats\":{\"H265\":[{\"format\":1600022,\"defn\":\"V640P\",\"profile\":\"MP4\",\"path\":\"\",\"url\":\"http://vod.sp-cdn.shopee.com/c3/98934353/103/A3oxOGcEAAxmnQwPEV0GACc.mp4\",\"width\":640,\"height\":1138,\"bitrate\":732706,\"size\":1023586,\"fps\":25.10246,\"duration\":9760,\"update_time\":1665426479}]},\"ab_test\":\"\"}","cover_image_id":""}],"product_items":[{"itemid":17839269862,"shopid":494676223,"name":"Serum Mụn SKINTIFIC Chính Hãng Rulya Anti Acne 20ml","image":"afd17f8a1920780ccd39a6dbb9e6f358","is_snapshot":1,"snapshotid":3472545210,"modelid":135025837391,"model_name":"","options":[""]}],"delete_reason":null,"delete_operator":null,"ItemRatingReply":null,"tags":null,"editable_date":null,"show_reply":null,"like_count":null,"liked":null,"sync_to_social":false,"detailed_rating":{"product_quality":5,"seller_service":null,"delivery_service":null},"exclude_scoring_due_low_logistic":false,"loyalty_info":null,"template_tags":["Công dụng","Khả năng thẩm thấu"],"has_template_tag":true,"sync_to_social_toggle":null,"sip_info":{"is_oversea":false,"origin_region":"vn"},"is_repeated_purchase":false,"display_variation_filter":null,"overall_fit":0,"is_normal_item":true,"viewed":null,"show_view":null,"sync_to_social_detail":null,"profile":null,"size_info_tags":null,"size_info_abt":"","image_data":[{"image_id":"5f3165e659bc550997fe0d76f2cc436d","cover_image_id":"5f3165e659bc550997fe0d76f2cc436d"}],"key_media":{"key_media_code":0,"key_media_id":""}},{"orderid":108188074573116,"itemid":17839269862,"cmtid":8660979461,"ctime":1655098448,"rating":1,"userid":474718798,"shopid":494676223,"comment":"Công dụng:giảm mụn\nMùi hương:khá thơm\nDành cho da:mọi loại da\n\nsản phẩm chất lượng tốt giao khá nhanh đánh giá 10/10","rating_star":5,"status":2,"mtime":1655098448,"editable":0,"opt":2,"filter":7,"mentioned":null,"is_hidden":false,"author_username":"2*****z","author_portrait":"191099b8cc1969fe72b123503062b509","author_shopid":474699221,"anonymous":true,"images":["vn-11134103-22060-cy5phrpoprdv1f"],"videos":[{"id":"vn_44c8b210-2e7d-4d55-8114-db46f7156749_000159","cover":"https://play-ws.vod.shopee.com/c3/98934353/103/Anoyuh4ApGoybgUh-AEAAEc.jpg","url":"https://play-ws.vod.shopee.com/c3/98934353/103/Anoy9a4AvOsybgUhIwIBAEY.mp4","duration":19085,"upload_time":null,"mms_ext":"{\"vid\":\"vn_44c8b210-2e7d-4d55-8114-db46f7156749_000159\",\"biz\":103,\"duration\":19280,\"create_time\":1655098348,\"serviceID\":2,\"cover\":\"http://play-ws.vod.shopee.com/c3/98934353/103/Anoyuh4ApGoybgUh-AEAAEc.jpg\",\"cover_list\":null,\"formats\":[{\"format\":1600005,\"defn\":\"V640P\",\"profile\":\"MP4\",\"path\":\"\",\"url\":\"http://play-ws.vod.shopee.com/c3/98934353/103/Anoy9a4AvOsybgUhIwIBAEY.mp4\",\"width\":576,\"height\":1024,\"bitrate\":602619,\"size\":1576378,\"fps\":25.05187,\"duration\":19280,\"update_time\":1655098358}],\"default_format\":{\"format\":600001,\"defn\":\"ORI\",\"profile\":\"MP4\",\"path\":\"\",\"url\":\"http://play-ws.vod.shopee.com/c3/98934353/103/AnoyHAkAOG0ybgUhLAIJAEY.mp4\",\"width\":576,\"height\":1024,\"bitrate\":1809992,\"size\":4642718,\"fps\":24.10232,\"duration\":19084,\"update_time\":1655098350},\"extend_formats\":{\"H265\":[{\"format\":1600018,\"defn\":\"V480P\",\"profile\":\"MP4\",\"path\":\"\",\"url\":\"http://play-ws.vod.shopee.com/c3/98934353/103/A3oyOWVoAFhNAkgTEX8AACY.mp4\",\"width\":480,\"height\":854,\"bitrate\":444854,\"size\":1319891,\"fps\":25.05187,\"duration\":19280,\"update_time\":1669970564},{\"format\":1600022,\"defn\":\"V640P\",\"profile\":\"MP4\",\"path\":\"\",\"url\":\"http://play-ws.vod.shopee.com/c3/98934353/103/A3oyOYxFAKgWA0gTEVgGACY.mp4\",\"width\":576,\"height\":1024,\"bitrate\":568077,\"size\":1692992,\"fps\":25.05187,\"duration\":19280,\"update_time\":1669970577}]},\"ab_test\":\"\"}","cover_image_id":""}],"product_items":[{"itemid":17839269862,"shopid":494676223,"name":"Serum Mụn SKINTIFIC Chính Hãng Rulya Anti Acne 20ml","image":"afd17f8a1920780ccd39a6dbb9e6f358","is_snapshot":1,"snapshotid":3573694431,"modelid":135025837391,"model_name":"","options":[""]}],"delete_reason":null,"delete_operator":null,"ItemRatingReply":{"orderid":108188074573116,"itemid":null,"cmtid":8660979461,"ctime":1655104672,"rating":null,"userid":494695801,"shopid":null,"comment":"SKINTIFIC cảm ơn bạn đã tin tưởng và ủng hộ! Nếu bạn có bất cứ vấn đề gì đều có thể nhắn tin với SKINTIFIC để có được giải đáp tận tình nhất. SKINTIFIC rất sẵn lòng được phục vụ bạn!","rating_star":null,"status":null,"mtime":1655104672,"editable":null,"opt":null,"filter":null,"mentioned":null,"is_hidden":false},"tags":[{"tag_id":2,"tag_description":"Chất lượng sản phẩm tuyệt vời"},{"tag_id":5,"tag_description":"Đóng gói sản phẩm rất đẹp và chắc chắn"},{"tag_id":6,"tag_description":"Shop phục vụ rất tốt"},{"tag_id":3,"tag_description":"Rất đáng tiền"},{"tag_id":4,"tag_description":"Thời gian giao hàng rất nhanh"}],"editable_date":1657690448,"show_reply":null,"like_count":null,"liked":null,"sync_to_social":false,"detailed_rating":{"product_quality":5,"seller_service":null,"delivery_service":null},"exclude_scoring_due_low_logistic":false,"loyalty_info":null,"template_tags":["Công dụng","Mùi hương","Dành cho da"],"has_template_tag":true,"sync_to_social_toggle":null,"sip_info":{"is_oversea":false,"origin_region":"vn"},"is_repeated_purchase":false,"display_variation_filter":null,"overall_fit":0,"is_normal_item":true,"viewed":null,"show_view":null,"sync_to_social_detail":null,"profile":null,"size_info_tags":null,"size_info_abt":"","image_data":[{"image_id":"vn-11134103-22060-cy5phrpoprdv1f","cover_image_id":"vn-11134103-22060-cy5phrpoprdv1f"}],"key_media":{"key_media_code":0,"key_media_id":""}},{"orderid":107571059276418,"itemid":17839269862,"cmtid":8541324676,"ctime":1654077039,"rating":1,"userid":355978284,"shopid":494676223,"comment":"Dành cho da:dầu mụn\nMùi hương:ko hắc","rating_star":5,"status":2,"mtime":1654077039,"editable":0,"opt":2,"filter":7,"mentioned":null,"is_hidden":false,"author_username":"yz3pany1le","author_portrait":"","author_shopid":355958707,"anonymous":false,"images":["vn-11134103-22060-j9l1vq4auadva8"],"videos":[{"id":"vn_ea7f9949-d449-49ba-8893-348382a65e5e_000155","cover":"https://play-ws.vod.shopee.com/vn_ea7f9949-d449-49ba-8893-348382a65e5e_000155.ori.jpg","url":"https://play-ws.vod.shopee.com/c3/98934353/103/AnoyXQoAYAOzegQh3QEOAEc.mp4","duration":3815,"upload_time":null,"mms_ext":"{\"vid\":\"vn_ea7f9949-d449-49ba-8893-348382a65e5e_000155\",\"biz\":103,\"duration\":3839,\"create_time\":1654077036,\"serviceID\":3,\"cover\":\"https://play-ws.vod.shopee.com/vn_ea7f9949-d449-49ba-8893-348382a65e5e_000155.ori.jpg\",\"cover_list\":null,\"formats\":[{\"format\":1600005,\"defn\":\"V640P\",\"profile\":\"MP4\",\"path\":\"\",\"url\":\"http://play-ws.vod.shopee.com/c3/98934353/103/AnoyXQoAYAOzegQh3QEOAEc.mp4\",\"width\":640,\"height\":1138,\"bitrate\":839529,\"size\":430555,\"fps\":25,\"duration\":3839,\"update_time\":1654077047}],\"default_format\":{\"format\":600001,\"defn\":\"ORI\",\"profile\":\"MP4\",\"path\":\"\",\"url\":\"http://play-ws.vod.shopee.com/c3/98934353/103/Anoy=EgAwHGyegQh5QEEAEY.mp4\",\"width\":720,\"height\":1280,\"bitrate\":2528491,\"size\":1272507,\"fps\":24.3771,\"duration\":3814,\"update_time\":1654077037},\"extend_formats\":{\"H265\":[{\"format\":1600022,\"defn\":\"V640P\",\"profile\":\"MP4\",\"path\":\"\",\"url\":\"http://play-ws.vod.shopee.com/c3/98934353/103/A3oxOMVrABAhxDQREX0CACc.mp4\",\"width\":640,\"height\":1138,\"bitrate\":699637,\"size\":407561,\"fps\":25.25773,\"duration\":3880,\"update_time\":1667742370}]},\"ab_test\":\"\"}","cover_image_id":""}],"product_items":[{"itemid":17839269862,"shopid":494676223,"name":"Serum Mụn SKINTIFIC Chính Hãng Rulya Anti Acne 20ml","image":"afd17f8a1920780ccd39a6dbb9e6f358","is_snapshot":1,"snapshotid":3558368908,"modelid":135025837391,"model_name":"","options":[""]}],"delete_reason":null,"delete_operator":null,"ItemRatingReply":{"orderid":107571059276418,"itemid":null,"cmtid":8541324676,"ctime":1656136824,"rating":null,"userid":494695801,"shopid":null,"comment":"SKINTIFIC cảm ơn bạn đã tin tưởng và ủng hộ! Nếu bạn có bất cứ vấn đề gì đều có thể nhắn tin với SKINTIFIC để có được giải đáp tận tình nhất. SKINTIFIC rất sẵn lòng được phục vụ bạn!","rating_star":null,"status":null,"mtime":1656136824,"editable":null,"opt":null,"filter":null,"mentioned":null,"is_hidden":false},"tags":[{"tag_id":2,"tag_description":"Chất lượng sản phẩm tuyệt vời"},{"tag_id":5,"tag_description":"Đóng gói sản phẩm rất đẹp và chắc chắn"},{"tag_id":6,"tag_description":"Shop phục vụ rất tốt"},{"tag_id":4,"tag_description":"Thời gian giao hàng rất nhanh"}],"editable_date":1656669039,"show_reply":null,"like_count":1,"liked":null,"sync_to_social":false,"detailed_rating":{"product_quality":5,"seller_service":null,"delivery_service":null},"exclude_scoring_due_low_logistic":false,"loyalty_info":null,"template_tags":["Công dụng","Mùi hương","Dành cho da"],"has_template_tag":true,"sync_to_social_toggle":null,"sip_info":{"is_oversea":false,"origin_region":"vn"},"is_repeated_purchase":false,"display_variation_filter":null,"overall_fit":0,"is_normal_item":true,"viewed":null,"show_view":null,"sync_to_social_detail":null,"profile":null,"size_info_tags":null,"size_info_abt":"","image_data":[{"image_id":"vn-11134103-22060-j9l1vq4auadva8","cover_image_id":"vn-11134103-22060-j9l1vq4auadva8"}],"key_media":{"key_media_code":0,"key_media_id":""}}],"item_rating_summary":{"rating_total":43,"rating_count":[0,1,1,1,40],"rcount_with_context":24,"rcount_with_image":19,"rcount_with_media":19,"rcount_local_review":43,"rcount_repeat_purchase":0,"rcount_overall_fit_small":0,"rcount_overall_fit_fit":0,"rcount_overall_fit_large":0,"rcount_oversea_review":0,"rcount_folded":0},"is_sip_item":false,"rcmd_algo":"BUNDLE:comment_search,RECALLER:comment_search_default,QUEUE:comment_search_default,ABTEST:2.a.3644@AD0,QUEUES:comment_search_default,NEWABTEST:0","downgrade_switch":false,"has_more":true,"show_local_review":false,"browsing_ui":"","enable_buyer_gallery_media":false,"user_latest_rating":null,"size_info_abt":"","top_ratings":[],"resize_image_abt":false,"purchase_bar_abt":"bucket_a"},"error":0,"error_msg":null}